excel_text/__init__.py
excel_text/_condition.py
excel_text/_elapsed.py
excel_text/_errors.py
excel_text/_factory.py
excel_text/_grammar.py
excel_text/_numbers.py
excel_text/_preprocess.py
excel_text/_tokens.py
excel_text/_visitor.py
excel_text/condition.py
excel_text/elapsed.py
excel_text/errors.py
excel_text/factory.py
excel_text/grammar.py
excel_text/numbers.py
excel_text/preprocess.py
excel_text/py.typed
excel_text/tokens.py
excel_text/version.py
excel_text/visitor.py
excel_text-1.0.0.dist-info/LICENCE
excel_text-1.0.0.dist-info/METADATA
excel_text-1.0.0.dist-info/WHEEL
excel_text-1.0.0.dist-info/top_level.txt
excel_text-1.0.0.dist-info/RECORD
