Metadata-Version: 2.1
Name: excel-text
Version: 1.0.0
Summary: Python implementation of Excel's `text` function
Author-email: Bart-Jan Hulsman <hulsmanbj@gmail.com>, Rudolf Byker <rudolfbyker@gmail.com>
Project-URL: repository, https://github.com/AutoActuary/excel-text
Classifier: Programming Language :: Python :: 3
Classifier: License :: OSI Approved :: MIT License
Classifier: Operating System :: OS Independent
Requires-Python: >=3.7
License-File: LICENCE
Requires-Dist: excel-dates (==1.*,>=1.0)
Requires-Dist: parsimonious (==0.10.*)
